edrag/__init__.py
edrag/edrag.py
edrag/evaluation.py
edrag/generation.py
edrag/indexing.py
edrag/models.py
edrag/retrieval.py
edrag/utils.py
edrag-0.1.0.dist-info/LICENSE
edrag-0.1.0.dist-info/METADATA
edrag-0.1.0.dist-info/WHEEL
edrag-0.1.0.dist-info/top_level.txt
edrag-0.1.0.dist-info/RECORD
